{
  "월": {
    "1": "",
    "2": "물1C\n(206)",
    "3": "",
    "4": "통과\n(101)",
    "5": "",
    "6": "통과\n(103)",
    "7": "통과\n(106)"
  },
  "화": {
    "1": "",
    "2": "물1C\n(206)",
    "3": "통과\n(104)",
    "4": "",
    "5": "물2\n(305)",
    "6": "",
    "7": "물1A\n(206)"
  },
  "수": {
    "1": "물1A\n(206)",
    "2": "",
    "3": "물1C\n(206)",
    "4": "",
    "5": "창체",
    "6": "창체",
    "7": ""
  },
  "목": {
    "1": "",
    "2": "통과\n(102)",
    "3": "",
    "4": "물2\n(305)",
    "5": "물1A\n(206)",
    "6": "물1C\n(206)",
    "7": ""
  },
  "금": {
    "1": "통과\n(107)",
    "2": "물2\n(305)",
    "3": "",
    "4": "물1A\n(206)",
    "5": "",
    "6": "통과\n(105)",
    "7": ""
  }
}